mi_paquete/__init__.py
mi_paquete/modulo.py
mi_paquete_xyz123-0.1.0.dist-info/licenses/LICENSE
mi_paquete_xyz123-0.1.0.dist-info/METADATA
mi_paquete_xyz123-0.1.0.dist-info/WHEEL
mi_paquete_xyz123-0.1.0.dist-info/top_level.txt
mi_paquete_xyz123-0.1.0.dist-info/RECORD
