Metadata-Version: 2.4
Name: mi_paquete_xyz123
Version: 0.1.0
Summary: Descripción corta de tu paquete
Author: Tu Nombre
Author-email: Tu Nombre <tu@email.com>
Classifier: Programming Language :: Python :: 3
Classifier: License :: OSI Approved :: MIT License
Classifier: Operating System :: OS Independent
Requires-Python: >=3.8
License-File: LICENSE
Dynamic: author
Dynamic: license-file
Dynamic: requires-python
